{
  "text": {
    "olá": 36,
    "oi": 35,
    "boa": 11,
    "tarde": 46,
    "como": 13,
    "vai": 53,
    "não": 32,
    "consigo": 14,
    "acessar": 3,
    "minha": 29,
    "conta": 15,
    "estou": 18,
    "com": 12,
    "problemas": 41,
    "para": 37,
    "logar": 24,
    "está": 19,
    "bloqueada": 10,
    "fazer": 20,
    "login": 25,
    "quero": 43,
    "mudar": 30,
    "meu": 28,
    "plano": 38,
    "alterar": 5,
    "de": 16,
    "assinatura": 8,
    "trocar": 51,
    "faço": 21,
    "o": 33,
    "aplicativo": 6,
    "funciona": 23,
    "app": 7,
    "abrindo": 1,
    "no": 31,
    "travou": 50,
    "abre": 0,
    "fechando": 22,
    "sozinho": 45,
    "em": 17,
    "abrir": 2,
    "quano": 42,
    "tento": 49,
    "até": 9,
    "logo": 26,
    "tchau": 47,
    "obrigado": 34,
    "mais": 27,
    "tenho": 48,
    "um": 52,
    "problema": 40,
    "preciso": 39,
    "ajuda": 4,
    "resolver": 44
  },
  "intent": {
    "saudacao": 6,
    "problema_acesso": 1,
    "problema_plano": 5,
    "problema_aplicativo": 2,
    "problema_aplicativo_nao_abre": 3,
    "despedida": 0,
    "problema_geral": 4
  },
  "response": null,
  "action_name": {
    "action_listen": 6,
    "action_restart": 7,
    "action_session_start": 9,
    "action_default_fallback": 4,
    "action_deactivate_loop": 1,
    "action_revert_fallback_events": 8,
    "action_default_ask_affirmation": 2,
    "action_default_ask_rephrase": 3,
    "action_two_stage_fallback": 10,
    "action_unlikely_intent": 11,
    "action_back": 0,
    "action_extract_slots": 5,
    "utter_despedida": 12,
    "utter_encaminhamento_atendente": 13,
    "utter_problema_acesso": 14,
    "utter_problema_aplicativo": 15,
    "utter_problema_aplicativo_nao_abre": 16,
    "utter_problema_plano": 17,
    "utter_saudacao": 18
  },
  "action_text": null,
  "intent_response_key": null
}